mnist_datasets/__init__.py
mnist_datasets/loader.py
mnist_datasets-0.14.dist-info/licenses/LICENSE
mnist_datasets-0.14.dist-info/METADATA
mnist_datasets-0.14.dist-info/WHEEL
mnist_datasets-0.14.dist-info/top_level.txt
mnist_datasets-0.14.dist-info/RECORD
