Metadata-Version: 2.4
Name: mnist_datasets
Version: 0.14
Summary: A Python module to load mnist_datasets from scratch
Home-page: https://github.com/ratulb/mnist_datasets
Author: Ratul Buragohain
Author-email: ratul75@hotmail.com
Classifier: Programming Language :: Python :: 3.10
Classifier: License :: OSI Approved :: MIT License
Classifier: Operating System :: OS Independent
Requires-Python: >=3.10, <3.13
License-File: LICENSE
Requires-Dist: numpy
Requires-Dist: tqdm
Dynamic: author
Dynamic: author-email
Dynamic: classifier
Dynamic: description
Dynamic: description-content-type
Dynamic: home-page
Dynamic: license-file
Dynamic: requires-dist
Dynamic: requires-python
Dynamic: summary
